include/state_defines.v

`define IDLE    6'b000001
`define GRANT_L 6'b000010
`define GRANT_N 6'b000100
`define GRANT_E 6'b001000
`define GRANT_W 6'b010000
`define GRANT_S 6'b100000

`define L_PORT 5'b00001
`define N_PORT 5'b00010
`define E_PORT 5'b00100
`define W_PORT 5'b01000
`define S_PORT 5'b10000

include/parameters.v

  // defining the flit ID -- One hot encoding
  `define HEADER  3'b001
  `define PAYLOAD 3'b010
  `define TAIL    3'b100

  // Specifying the FIFO parameters
  `define FIFO_DEPTH 'd4               // 4 flits capacity
  `define PTR_SIZE   `FIFO_DEPTH       // Controls reading and writing (for full and empty) >> Depends on the FIFO_DEPTH
  `define DATA_WIDTH 'd32              // # of data bits with parity

rtl/Arbiter.sv

module Arbiter (clk, 
                rst, 
                Req_N, Req_E, Req_W, Req_S, Req_L, // From LBDR modules (routing logic)
                DCTS, // Getting the CTS signal from the input FIFO of the next router/NI (for hand-shaking)
                Grant_N, Grant_E, Grant_W, Grant_S, Grant_L, // Grants given to LBDR (routing logic) requests (encoded as one-hot)
                Xbar_sel, // select lines for XBAR (crossbar switch)
                RTS // Valid output which is sent to the next router/NI to specify that the data on the output port is valid
            );

    // --                                                                        next
    // --                                     Arbiter                        router or NI
    // --                     --- ---------------------------- ----          ----
    // --   from LBDR  --->  |Req(s)                           RTS | -----> |DRTS
    // --    To FIFO   <---  |Grant(s)                         DCTS| <----- |CTS
    // --    to XBAR   <---  |Xbar_sel                             |        | 
    // --                     --- ---------------------------- ----          ----

    //  --------------------------------------------------------------------------------------------
    //  -- an example of a request/grant + handshake process with next router or NI

    // --CLK      _|'|_|'|_|'|_|'|_|'|_|'|_|'|_|'|_|'|_|'|_|'|_|'|_|'|_|'|__

    // -- Req     _____|'''''''''''''''''''''''''''''''''''''''''''|________

    // --         _________ ___________________ _______ _______ _______ ____
    // -- TX      _________X_______HEADER______X_Body__X_Body__X__Tail_X____

    // -- Grant   _________________________|'''|___|'''|___|'''|____________

    // --  RTS    _________|'''''''''''''''''''|___|'''''''|___|'''''''|____

    // --  DCTS   _________________________|'''|_______|'''|_______|'''|____  (CTS (DCTS) is always maximum 1 clock cycle!)
    // --                                  |<---------clear----------->|
    // --                                  |         to send           |
    //  --------------------------------------------------------------------------------------------

    input   clk, rst;
    input   Req_N, Req_E, Req_W, Req_S, Req_L;
    input   DCTS;
    output  logic Grant_N, Grant_E, Grant_W, Grant_S, Grant_L;
    output  logic [4:0] Xbar_sel;
    output  logic RTS;

    typedef enum bit [5:0] {IDLE = 6'b000001, Local = 6'b000010, North = 6'b000100, East = 6'b001000, West = 6'b010000, South = 6'b100000} STATE_TYPE;

    STATE_TYPE state = IDLE;
    STATE_TYPE state_in = IDLE;
    STATE_TYPE next_state = IDLE;

    logic RTS_FF = 0;
    logic RTS_FF_in = 0;


    // Sequential part
    // rst is active high!
    always @(posedge clk) begin

     if (rst) begin
        state  <= IDLE;
        RTS_FF <= 0;
     end
     else begin
        // no grant given yet, it might be that there is no request to 
        // arbiter or request is there, but the next router's/NI's FIFO is full
        state <= state_in;
        RTS_FF <= RTS_FF_in;   
      end
    end 


    // Anything below here is pure combinational

    assign RTS = RTS_FF;

    always @(RTS_FF, DCTS, state, next_state) begin
        if (RTS_FF && !DCTS) 
            state_in <= state;
        else
            state_in <= next_state;
    end


    always @(state, RTS_FF, DCTS) begin
        if (state == IDLE) begin 
            RTS_FF_in <= 0;
            // if there was a grant given to one of the inputs, 
            // tell the next router/NI that the output data is valid
        end
        else begin
            if (RTS_FF && DCTS)
                RTS_FF_in <= 0;
            else 
                RTS_FF_in <= 1;
        end
    end

    // Sets the grants using round robin 
    // the order is   L --> N --> E --> W --> S  and  back to L
    always @(state, Req_N, Req_E, Req_W, Req_S, Req_L, DCTS, RTS_FF) begin
        Grant_N  <= 0;
        Grant_E  <= 0;
        Grant_W  <= 0;
        Grant_S  <= 0;
        Grant_L  <= 0;
        Xbar_sel <= 5'b00000; 

        case(state)
            IDLE: begin
                Xbar_sel<= 5'b00000; 
                
                if (Req_L) 
                    next_state <= Local;
                else if (Req_N) 
                    next_state <= North;         
                else if (Req_E) 
                    next_state <= East;
                else if (Req_W) 
                    next_state <= West;
                else if (Req_S) 
                    next_state <= South;
                else
                    next_state <= IDLE;
            end

            North: begin
                Grant_N <= DCTS & RTS_FF ;
                Xbar_sel<= 5'b00001;
                
                if (Req_N)  
                    next_state <= North; 
                else if (Req_E) 
                    next_state <= East;
                else if (Req_W) 
                    next_state <= West;
                else if (Req_S) 
                    next_state <= South;
                else if (Req_L) 
                    next_state <= Local;
                else
                    next_state <= IDLE; 
            end 

            East: begin
                Grant_E <= DCTS & RTS_FF;
                Xbar_sel<= 5'b00010;
                
                if (Req_E)  
                    next_state <= East; 
                else if (Req_W) 
                    next_state <= West;
                else if (Req_S) 
                    next_state <= South;
                else if (Req_L) 
                    next_state <= Local;
                else if (Req_N) 
                    next_state <= North;
                else
                    next_state <= IDLE; 
            end 

            West: begin
                Grant_W <= DCTS & RTS_FF;
                Xbar_sel<= 5'b00100;
                
                if (Req_W ) 
                    next_state <= West; 
                else if (Req_S ) 
                    next_state <= South;
                else if (Req_L ) 
                    next_state <= Local;
                else if (Req_N ) 
                    next_state <= North;
                else if (Req_E ) 
                    next_state <= East;
                else
                    next_state <= IDLE; 
            end

            South: begin
                Grant_S <= DCTS & RTS_FF;
                Xbar_sel<= 5'b01000;
                
                if (Req_S )
                    next_state <= South; 
                else if (Req_L)
                    next_state <= Local;
                else if (Req_N)
                    next_state <= North;
                else if (Req_E)
                    next_state <= East;
                else if (Req_W)
                    next_state <= West;
                else
                    next_state <= IDLE; 
            end

            default: begin // Including Local and invalid states (non- onehot!)
                Grant_L <= DCTS & RTS_FF;
                Xbar_sel<= 5'b10000;
                
                if (Req_L)
                    next_state <= Local; 
                else if (Req_N)
                    next_state <= North;         
                else if (Req_E )
                    next_state <= East;
                else if (Req_W )
                    next_state <= West;
                else if (Req_S )
                    next_state <= South;
                else
                    next_state <= IDLE; 
            end
        endcase
    end

endmodule

tb/bfm_arbiter.sv
// `include "../include/parameters.v"
// `include "../include/state_defines.v"

module bfm_arbiter(bfm_clk, bfm_command, bfm_grant);

  input bfm_clk;
  input [5:0] bfm_command;
  
  output logic bfm_grant;
  
  // Declaring the port variables for DUT
  wire          clk;
  logic         rst;
  logic         Nreq = 0;
  logic         Ereq = 0;
  logic         Wreq = 0;
  logic         Sreq = 0;
  logic         Lreq = 0; // Will be connected to (Req_N, Req_E, Req_W, Req_S, Req_L) of Arbiter DUT, respectively!
  logic         DCTS = 1; // Let's assume the input FIFO of next router/NI is always ready to receive data (infinite FIFO space assumption)!! To be updated later maybe!!
  logic [4:0]   Xbar_sel = 0;
  logic         RTS = 0;
  

  // Specifying timeout period
  parameter TIMEOUT = 5;
  integer loop;
  
  // always @(negedge clk) begin
  //   if(!rst) begin // Reset 
  //     Llength = TIMEOUT;
  //     Nlength = TIMEOUT;
  //     Elength = TIMEOUT;
  //     Wlength = TIMEOUT;
  //     Slength = TIMEOUT;
  //     for(loop = 0; loop < TIMEOUT-1; loop = loop + 1) begin
  //       @(negedge clk) begin
  //         {Lflit_id, Nflit_id, Eflit_id, Wflit_id, Sflit_id} = {`PAYLOAD, `PAYLOAD, `PAYLOAD, `PAYLOAD, `PAYLOAD};
  //       end
  //     end
  //     {Lflit_id, Nflit_id, Eflit_id, Wflit_id, Sflit_id} = {`TAIL, `TAIL, `TAIL, `TAIL, `TAIL};
  //   end
  // end
  
  // Specifying the single pulse request parameter
  parameter NR = 3'b000,        // No request
            RS = 3'b001,        // Request to south
            RW = 3'b010,        // Request to west
            RE = 3'b011,        // Request to east
            RN = 3'b100,        // Request to north
            RL = 3'b101;        // Request to local
            
  // Specifying the continuous pulse(with access time) request parameter
  // Adding Extra bit for FSM Transition. To differentiate L-->N(00001), N-->L(10001). MSB stands for forward/backward
  parameter NRQ = 5'b00000,           // No request
            RLN = 5'b00001,           // Local to north
            RLE = 5'b00010,           // Local to east
            RLW = 5'b00011,           // Local to west
            RLS = 5'b00100,           // Local to south
            RLL = 5'b00101,           // Local to local
            RNE = 5'b00110,           // North to east
            RNW = 5'b00111,           // North to west
            RNS = 5'b01000,           // North to south
            RNL = 5'b10001,           // North to local
            RNN = 5'b01001,           // North to north
            REW = 5'b01010,           // East to west
            RES = 5'b01011,           // East to south
            REL = 5'b10010,           // East to local
            REN = 5'b10110,           // East to north
            REE = 5'b01100,           // East to east
            RWS = 5'b01101,           // West to south
            RWL = 5'b10011,           // West to local
            RWN = 5'b10111,           // West to north
            RWE = 5'b11010,           // West to east
            RWW = 5'b01110,           // West to west
            RSL = 5'b10100,           // South to local
            RSN = 5'b11000,           // South to north
            RSE = 5'b11011,           // South to east
            RSW = 5'b11101,           // South to west
            RSS = 5'b01111;           // South to south
            
  // BFM commands Declaration
  parameter NOREQ1 = 6'd1,
            REQFL  = 6'd2,
            REQFN  = 6'd3,
            REQFE  = 6'd4,
            REQFW  = 6'd5,
            REQFS  = 6'd6,
            NOREQ2 = 6'd7,
            REQFLN = 6'd8,
            REQFLE = 6'd9,
            REQFLW = 6'd10,
            REQFLS = 6'd11,
            REQFLL = 6'd12,
            REQFNE = 6'd13,
            REQFNW = 6'd14,
            REQFNS = 6'd15,
            REQFNL = 6'd16,
            REQFNN = 6'd17,
            REQFEW = 6'd18,
            REQFES = 6'd19,
            REQFEL = 6'd20,
            REQFEN = 6'd21,
            REQFEE = 6'd22,
            REQFWS = 6'd23,
            REQFWL = 6'd24,
            REQFWN = 6'd25,
            REQFWE = 6'd26,
            REQFWW = 6'd27,
            REQFSL = 6'd28,
            REQFSN = 6'd29,
            REQFSE = 6'd30,
            REQFSW = 6'd31,
            REQFSS = 6'd32;
            
  assign clk = bfm_clk;
  
  // Instantiate ARBITER DUT              

  Arbiter DUT (clk, 
                rst, 
                Nreq, Ereq, Wreq, Sreq, Lreq, // From LBDR modules (routing logic)
                DCTS, // Getting the CTS signal from the input FIFO of the next router/NI (for hand-shaking)
                Grant_N, Grant_E, Grant_W, Grant_S, Grant_L, // Grants given to LBDR (routing logic) requests (encoded as one-hot)
                Xbar_sel, // select lines for XBAR (crossbar switch)
                RTS // Valid output which is sent to the next router/NI to specify that the data on the output port is valid
            ); 


  // Task to generate reset
  task reset;
    begin
      rst                                 = 1;
      {Nreq, Ereq, Wreq, Sreq, Lreq}      = 0;
      DCTS                                = 1;

      @(negedge clk);
        if( {Grant_N, Grant_E, Grant_W, Grant_S, Grant_L} != 5'b00000) begin // IDLE
          $display("Reset is not working\n");
          $display("Error at time %0t", $time);
          $stop; 
        end
        $display("TIME:%0t Reset is working\n", $time);
        repeat(2)
          @(negedge clk);
        rst = 0;
    end
  endtask
  
  // Task to request buffer for first time -- single pulse
  task request1;
    input [2:0] data;
    begin
      @(negedge clk) begin
        if(data == 0) begin
          {Nreq, Ereq, Wreq, Sreq, Lreq} = 0;
        end
        else begin
          {Nreq, Ereq, Wreq, Sreq, Lreq} = (1 << (data-1)); // To assert the particular bit since data == 0 is used for IDLE
        end
      end
    end
  endtask
  
  // Task to request buffer for first time withoout last request -- continuous pulse requested by any buffer
  task request2;
    input Nr, Er, Wr, Sr, Lr;
    input [4:0] data;
    begin
      @(negedge clk) begin
        if(data == 0) begin
          {Nreq, Ereq, Wreq, Sreq, Lreq} = 0;
        end
        else begin
          {Nreq, Ereq, Wreq, Sreq, Lreq} = {Nr, Er, Wr, Sr, Lr};
        end
      end
      
      repeat(TIMEOUT+2) //Repeating the request for a particular buffer till timeout occurs followed by round robin priority request
        @(negedge clk);
    end
  endtask
  
  // Sampling and executing Commands
  always @(posedge clk) begin
    case(bfm_command)
      NOREQ1 :
        begin
          bfm_grant = 1'b0;
          request1(NR);
          bfm_grant = 1'b1;
        end
      REQFL :
        begin
          bfm_grant = 1'b0;
          request1(RL);
          request1(NR);
          bfm_grant = 1'b1;
        end
      REQFN :
        begin
          bfm_grant = 1'b0;
          request1(RN);
          request1(NR);
          bfm_grant = 1'b1;
        end
      REQFE :
        begin
          bfm_grant = 1'b0;
          request1(RE);
          request1(NR);
          bfm_grant = 1'b1;
        end
      REQFW :
        begin
          bfm_grant = 1'b0;
          request1(RW);
          request1(NR);
          bfm_grant = 1'b1;
        end
      REQFS :
        begin
          bfm_grant = 1'b0;
          request1(RS);
          request1(NR);
          bfm_grant = 1'b1;
        end
      NOREQ2 :
        begin
          bfm_grant = 1'b0;
          request2(0, 0, 0, 0, 0, NRQ);
          bfm_grant = 1'b1;
        end
      REQFLN :
        begin
          bfm_grant = 1'b0;
          request2(1, 1, 1, 1, 1, RLN);
          bfm_grant = 1'b1;
        end
      REQFLE :
        begin
          bfm_grant = 1'b0;
          request2(1, 0, 1, 1, 1, RLE);
          bfm_grant = 1'b1;
        end
      REQFLW :
        begin
          bfm_grant = 1'b0;
          request2(0, 0, 0, 1, 0, RLW);
          bfm_grant = 1'b1;
        end
      REQFLS :
        begin
          bfm_grant = 1'b0;
          request2(1, 0, 0, 0, 1, RLS);
          bfm_grant = 1'b1;
        end
      REQFLL :
        begin
          bfm_grant = 1'b0;
          request2(1, 0, 0, 0, 0, RLL);
          bfm_grant = 1'b1;
        end
      REQFNE :
        begin
          bfm_grant = 1'b0;
          request2(1, 1, 1, 1, 1, RNE);
          bfm_grant = 1'b1;
        end
      REQFNW :
        begin
          bfm_grant = 1'b0;
          request2(1, 1, 0, 1, 1, RNW);
          bfm_grant = 1'b1;
        end
      REQFNS :
        begin
          bfm_grant = 1'b0;
          request2(1, 1, 0, 0, 1, RNS);
          bfm_grant = 1'b1;
        end
      REQFNL :
        begin
          bfm_grant = 1'b0;
          request2(1, 0, 0, 0, 0, RNL);
          bfm_grant = 1'b1;
        end
      REQFNN :
        begin
          bfm_grant = 1'b0;
          request2(0, 1, 0, 0, 0, RNN);
          bfm_grant = 1'b1;
        end
      REQFEW :
        begin
          bfm_grant = 1'b0;
          request2(1, 1, 1, 1, 1, REW);
          bfm_grant = 1'b1;
        end
      REQFES :
        begin
          bfm_grant = 1'b0;
          request2(1, 1, 1, 0, 1, RES);
          bfm_grant = 1'b1;
        end
      REQFEL :
        begin
          bfm_grant = 1'b0;
          request2(1, 1, 1, 0, 0, REL);
          bfm_grant = 1'b1;
        end
      REQFEN :
        begin
          bfm_grant = 1'b0;
          request2(0, 1, 1, 0, 0, REN);
          bfm_grant = 1'b1;
        end
      REQFEE :
        begin
          bfm_grant = 1'b0;
          request2(0, 0, 1, 0, 0, REE);
          bfm_grant = 1'b1;
        end
      REQFWS :
        begin
          bfm_grant = 1'b0;
          request2(1, 1, 1, 1, 1, RWS);
          bfm_grant = 1'b1;
        end
      REQFWL :
        begin
          bfm_grant = 1'b0;
          request2(1, 1, 1, 1, 0, RWL);
          bfm_grant = 1'b1;
        end
      REQFWN :
        begin
          bfm_grant = 1'b0;
          request2(0, 1, 1, 1, 0, RWN);
          bfm_grant = 1'b1;
        end
      REQFWE :
        begin
          bfm_grant = 1'b0;
          request2(0, 0, 1, 1, 0, RWE);
          bfm_grant = 1'b1;
        end
      REQFWW :
        begin
          bfm_grant = 1'b0;
          request2(0, 0, 0, 1, 0, RWW);
          bfm_grant = 1'b1;
        end
      REQFSL :
        begin
          bfm_grant = 1'b0;
          request2(1, 0, 0, 0, 0, RSL);
          bfm_grant = 1'b1;
        end
      REQFSN :
        begin
          bfm_grant = 1'b0;
          request2(0, 1, 0, 0, 0, RSN);
          bfm_grant = 1'b1;
        end
      REQFSE :
        begin
          bfm_grant = 1'b0;
          request2(0, 0, 1, 0, 0, RSE);
          bfm_grant = 1'b1;
        end
      REQFSW :
        begin
          bfm_grant = 1'b0;
          request2(0, 0, 0, 1, 0, RSW);
          bfm_grant = 1'b1;
        end
      REQFSS :
        begin
          bfm_grant = 1'b0;
          request2(0, 0, 0, 0, 1, RSS);
          bfm_grant = 1'b1;
        end
    endcase
  end


  // Properties and Assertions and Coverage Directives (for Shayan tool)
  // These should be auto-generated using the script !!

  `include "../properties_sva/Arbiter_properties.sva"

  
endmodule

tb/Arbiter_tb_req_grant_check.sv

module Arbiter_tb_req_grant_check();

  // Declaring the port variables for DUT
  reg bfm_clk;
  reg [5:0] bfm_command;
  
  wire bfm_grant;
  
  // BFM commands Declaration
  parameter NOREQ1 = 6'd1,
            REQFL  = 6'd2,
            REQFN  = 6'd3,
            REQFE  = 6'd4,
            REQFW  = 6'd5,
            REQFS  = 6'd6,
            NOREQ2 = 6'd7,
            REQFLN = 6'd8,
            REQFLE = 6'd9,
            REQFLW = 6'd10,
            REQFLS = 6'd11,
            REQFLL = 6'd12,
            REQFNE = 6'd13,
            REQFNW = 6'd14,
            REQFNS = 6'd15,
            REQFNL = 6'd16,
            REQFNN = 6'd17,
            REQFEW = 6'd18,
            REQFES = 6'd19,
            REQFEL = 6'd20,
            REQFEN = 6'd21,
            REQFEE = 6'd22,
            REQFWS = 6'd23,
            REQFWL = 6'd24,
            REQFWN = 6'd25,
            REQFWE = 6'd26,
            REQFWW = 6'd27,
            REQFSL = 6'd28,
            REQFSN = 6'd29,
            REQFSE = 6'd30,
            REQFSW = 6'd31,
            REQFSS = 6'd32;

  // Instantiate BFM
  bfm_arbiter BFM (bfm_clk, bfm_command, bfm_grant);
  
  // Specify the CYCLE parameter
  parameter CYCLE = 10;
  
  // Generating Clock of period 10ns
  initial begin
    bfm_clk = 0;
    forever
      #(CYCLE/2) bfm_clk = ~bfm_clk;
  end
  
  // Applying Commands
  initial begin : SIM
    BFM.reset;
    
    bfm_command = NOREQ1;
    @(posedge bfm_grant);

    bfm_command = REQFL;
    @(posedge bfm_grant);

    bfm_command = REQFN;
    @(posedge bfm_grant);

    bfm_command = REQFE;
    @(posedge bfm_grant);

    bfm_command = REQFW;
    @(posedge bfm_grant);

    bfm_command = REQFS;
    @(posedge bfm_grant);

    bfm_command = NOREQ2;
    @(posedge bfm_grant);

    bfm_command = REQFLN;
    @(posedge bfm_grant);

    bfm_command = REQFNE;
    @(posedge bfm_grant);

    bfm_command = REQFEW;
    @(posedge bfm_grant);

    bfm_command = REQFWS;
    @(posedge bfm_grant);

    bfm_command = REQFSL;
    @(posedge bfm_grant);

    bfm_command = REQFLL;
    @(posedge bfm_grant);

    bfm_command = REQFLE;
    @(posedge bfm_grant);

    bfm_command = REQFES;
    @(posedge bfm_grant);

    bfm_command = REQFSN;
    @(posedge bfm_grant);

    bfm_command = REQFNN;
    @(posedge bfm_grant);

    bfm_command = REQFNW;
    @(posedge bfm_grant);

    bfm_command = REQFWL;
    @(posedge bfm_grant);

    bfm_command = REQFLW;
    @(posedge bfm_grant);

    bfm_command = REQFWE;
    @(posedge bfm_grant);

    bfm_command = REQFEE;
    @(posedge bfm_grant);

    bfm_command = REQFEN;
    @(posedge bfm_grant);

    bfm_command = REQFNL;
    @(posedge bfm_grant);

    bfm_command = REQFLS;
    @(posedge bfm_grant);

    bfm_command = REQFSS;
    @(posedge bfm_grant);

    bfm_command = REQFSW;
    @(posedge bfm_grant);

    bfm_command = REQFWW;
    @(posedge bfm_grant);

    bfm_command = REQFWN;
    @(posedge bfm_grant);

    bfm_command = REQFNS;
    @(posedge bfm_grant);

    bfm_command = REQFSE;
    @(posedge bfm_grant);

    bfm_command = REQFEL;
    @(posedge bfm_grant);

    bfm_command = NOREQ2;
    @(posedge bfm_grant);

    //For toggle coverage of reset
    BFM.reset;

    $display("\n ****** Simulation Complete ********** \n");
    #(CYCLE * 2); 
    $stop;
  
  end


endmodule

traces/wave_dumps_req_grant_check.vcd
$date
	Sat Feb  6 12:06:32 2021
$end
$version
	QuestaSim Version 10.6_1
$end
$timescale
	1ns
$end

$scope module Arbiter_tb_req_grant_check $end

$scope module BFM $end

$scope module DUT $end
$var wire 1 ! clk $end
$var wire 1 " rst $end
$var wire 1 # Req_N $end
$var wire 1 $ Req_E $end
$var wire 1 % Req_W $end
$var wire 1 & Req_S $end
$var wire 1 ' Req_L $end
$var wire 1 ( DCTS $end
$var reg 1 ) Grant_N $end
$var reg 1 * Grant_E $end
$var reg 1 + Grant_W $end
$var reg 1 , Grant_S $end
$var reg 1 - Grant_L $end
$var reg 5 . Xbar_sel [4:0] $end
$var reg 1 / RTS $end
$var reg 6 0 state [5:0] $end
$var reg 6 1 state_in [5:0] $end
$var reg 6 2 next_state [5:0] $end
$var reg 1 3 RTS_FF $end
$var reg 1 4 RTS_FF_in $end
$upscope $end
$upscope $end
$upscope $end
$enddefinitions $end
#0
$dumpvars
0)
0*
0+
0,
0-
b0 .
0/
b1 0
b1 1
b1 2
03
04
0!
1"
0#
0$
0%
0&
0'
1(
$end
#5
1!
#10
0!
#15
1!
#20
0!
0"
#25
1!
#30
0!
#35
1!
#40
0!
1#
b100 2
b100 1
#45
1!
b100 0
14
b1 .
#50
0!
0#
b0 .
b1 .
b1 2
b1 1
#55
1!
b1 0
13
1/
04
b0 .
#60
0!
1$
b1000 2
b1000 1
#65
1!
b1000 0
03
0/
14
b10 .
#70
0!
0$
b0 .
b10 .
b1 2
b1 1
#75
1!
b1 0
13
1/
04
b0 .
#80
0!
1%
b10000 2
b10000 1
#85
1!
b10000 0
03
0/
14
b100 .
#90
0!
0%
b0 .
b100 .
b1 2
b1 1
#95
1!
b1 0
13
1/
04
b0 .
#100
0!
1&
b100000 2
b100000 1
#105
1!
b100000 0
03
0/
14
b1000 .
#110
0!
0&
b0 .
b1000 .
b1 2
b1 1
#115
1!
b1 0
13
1/
04
b0 .
#120
0!
1'
b10 2
b10 1
#125
1!
b10 0
03
0/
14
b10000 .
#130
0!
0'
b0 .
b10000 .
b1 2
b1 1
#135
1!
b1 0
13
1/
04
b0 .
#140
0!
#145
1!
03
0/
#150
0!
#155
1!
#160
0!
#165
1!
#170
0!
#175
1!
#180
0!
#185
1!
#190
0!
#195
1!
#200
0!
#205
1!
#210
0!
#215
1!
#220
0!
1'
1&
1%
1$
1#
b10 2
b10 1
#225
1!
b10 0
14
b10000 .
#230
0!
#235
1!
13
1/
04
b0 .
1-
b10000 .
#240
0!
#245
1!
03
0/
14
0-
b0 .
b10000 .
#250
0!
#255
1!
13
1/
04
b0 .
1-
b10000 .
#260
0!
#265
1!
03
0/
14
0-
b0 .
b10000 .
#270
0!
#275
1!
13
1/
04
b0 .
1-
b10000 .
#280
0!
#285
1!
03
0/
14
0-
b0 .
b10000 .
#290
0!
#295
1!
13
1/
04
b0 .
1-
b10000 .
#300
0!
#305
1!
03
0/
14
0-
b0 .
b10000 .
#310
0!
#315
1!
13
1/
04
b0 .
1-
b10000 .
#320
0!
#325
1!
03
0/
14
0-
b0 .
b10000 .
#330
0!
#335
1!
13
1/
04
b0 .
1-
b10000 .
#340
0!
#345
1!
03
0/
14
0-
b0 .
b10000 .
#350
0!
#355
1!
13
1/
04
b0 .
1-
b10000 .
#360
0!
#365
1!
03
0/
14
0-
b0 .
b10000 .
#370
0!
#375
1!
13
1/
04
b0 .
1-
b10000 .
#380
0!
#385
1!
03
0/
14
0-
b0 .
b10000 .
#390
0!
#395
1!
13
1/
04
b0 .
1-
b10000 .
#400
0!
#405
1!
03
0/
14
0-
b0 .
b10000 .
#410
0!
#415
1!
13
1/
04
b0 .
1-
b10000 .
#420
0!
#425
1!
03
0/
14
0-
b0 .
b10000 .
#430
0!
#435
1!
13
1/
04
b0 .
1-
b10000 .
#440
0!
#445
1!
03
0/
14
0-
b0 .
b10000 .
#450
0!
#455
1!
13
1/
04
b0 .
1-
b10000 .
#460
0!
#465
1!
03
0/
14
0-
b0 .
b10000 .
#470
0!
#475
1!
13
1/
04
b0 .
1-
b10000 .
#480
0!
#485
1!
03
0/
14
0-
b0 .
b10000 .
#490
0!
#495
1!
13
1/
04
b0 .
1-
b10000 .
#500
0!
#505
1!
03
0/
14
0-
b0 .
b10000 .
#510
0!
#515
1!
13
1/
04
b0 .
1-
b10000 .
#520
0!
#525
1!
03
0/
14
0-
b0 .
b10000 .
#530
0!
#535
1!
13
1/
04
b0 .
1-
b10000 .
#540
0!
0'
0&
0%
0$
0-
b0 .
1-
b10000 .
b100 2
b100 1
#545
1!
b100 0
03
0/
14
0-
b0 .
b1 .
#550
0!
#555
1!
13
1/
04
b0 .
1)
b1 .
#560
0!
#565
1!
03
0/
14
0)
b0 .
b1 .
#570
0!
#575
1!
13
1/
04
b0 .
1)
b1 .
#580
0!
#585
1!
03
0/
14
0)
b0 .
b1 .
#590
0!
#595
1!
13
1/
04
b0 .
1)
b1 .
#600
0!
#605
1!
03
0/
14
0)
b0 .
b1 .
#610
0!
#615
1!
13
1/
04
b0 .
1)
b1 .
#620
0!
#625
1!
03
0/
14
0)
b0 .
b1 .
#630
0!
#635
1!
13
1/
04
b0 .
1)
b1 .
#640
0!
#645
1!
03
0/
14
0)
b0 .
b1 .
#650
0!
#655
1!
13
1/
04
b0 .
1)
b1 .
#660
0!
#665
1!
03
0/
14
0)
b0 .
b1 .
#670
0!
#675
1!
13
1/
04
b0 .
1)
b1 .
#680
0!
#685
1!
03
0/
14
0)
b0 .
b1 .
#690
0!
#695
1!
13
1/
04
b0 .
1)
b1 .
#700
0!
1'
1&
1%
0)
b0 .
1)
b1 .
#705
1!
03
0/
14
0)
b0 .
b1 .
#710
0!
#715
1!
13
1/
04
b0 .
1)
b1 .
#720
0!
#725
1!
03
0/
14
0)
b0 .
b1 .
#730
0!
#735
1!
13
1/
04
b0 .
1)
b1 .
#740
0!
#745
1!
03
0/
14
0)
b0 .
b1 .
#750
0!
#755
1!
13
1/
04
b0 .
1)
b1 .
#760
0!
#765
1!
03
0/
14
0)
b0 .
b1 .
#770
0!
#775
1!
13
1/
04
b0 .
1)
b1 .
#780
0!
0&
1$
0)
b0 .
1)
b1 .
#785
1!
03
0/
14
0)
b0 .
b1 .
#790
0!
#795
1!
13
1/
04
b0 .
1)
b1 .
#800
0!
#805
1!
03
0/
14
0)
b0 .
b1 .
#810
0!
#815
1!
13
1/
04
b0 .
1)
b1 .
#820
0!
#825
1!
03
0/
14
0)
b0 .
b1 .
#830
0!
#835
1!
13
1/
04
b0 .
1)
b1 .
#840
0!
#845
1!
03
0/
14
0)
b0 .
b1 .
#850
0!
#855
1!
13
1/
04
b0 .
1)
b1 .
#860
0!
0'
0%
0#
0)
b0 .
1)
b1 .
b1000 2
b1000 1
#865
1!
b1000 0
03
0/
14
0)
b0 .
b10 .
#870
0!
#875
1!
13
1/
04
b0 .
1*
b10 .
#880
0!
#885
1!
03
0/
14
0*
b0 .
b10 .
#890
0!
#895
1!
13
1/
04
b0 .
1*
b10 .
#900
0!
#905
1!
03
0/
14
0*
b0 .
b10 .
#910
0!
#915
1!
13
1/
04
b0 .
1*
b10 .
#920
0!
#925
1!
03
0/
14
0*
b0 .
b10 .
#930
0!
#935
1!
13
1/
04
b0 .
1*
b10 .
#940
0!
#945
1!
03
0/
14
0*
b0 .
b10 .
#950
0!
#955
1!
13
1/
04
b0 .
1*
b10 .
#960
0!
#965
1!
03
0/
14
0*
b0 .
b10 .
#970
0!
#975
1!
13
1/
04
b0 .
1*
b10 .
#980
0!
#985
1!
03
0/
14
0*
b0 .
b10 .
#990
0!
#995
1!
13
1/
04
b0 .
1*
b10 .
#1000
0!
#1005
1!
03
0/
14
0*
b0 .
b10 .
#1010
0!
#1015
1!
13
1/
04
b0 .
1*
b10 .
#1020
0!
1'
1&
1#
0*
b0 .
1*
b10 .
#1025
1!
03
0/
14
0*
b0 .
b10 .
#1030
0!
#1035
1!
13
1/
04
b0 .
1*
b10 .
#1040
0!
#1045
1!
03
0/
14
0*
b0 .
b10 .
#1050
0!
#1055
1!
13
1/
04
b0 .
1*
b10 .
#1060
0!
#1065
1!
03
0/
14
0*
b0 .
b10 .
#1070
0!
#1075
1!
13
1/
04
b0 .
1*
b10 .
#1080
0!
#1085
1!
03
0/
14
0*
b0 .
b10 .
#1090
0!
#1095
1!
13
1/
04
b0 .
1*
b10 .
#1100
0!
0'
1%
0*
b0 .
1*
b10 .
#1105
1!
03
0/
14
0*
b0 .
b10 .
#1110
0!
#1115
1!
13
1/
04
b0 .
1*
b10 .
#1120
0!
#1125
1!
03
0/
14
0*
b0 .
b10 .
#1130
0!
#1135
1!
13
1/
04
b0 .
1*
b10 .
#1140
0!
#1145
1!
03
0/
14
0*
b0 .
b10 .
#1150
0!
#1155
1!
13
1/
04
b0 .
1*
b10 .
#1160
0!
#1165
1!
03
0/
14
0*
b0 .
b10 .
#1170
0!
#1175
1!
13
1/
04
b0 .
1*
b10 .
#1180
0!
0%
0$
0#
0*
b0 .
1*
b10 .
b100000 2
b100000 1
#1185
1!
b100000 0
03
0/
14
0*
b0 .
b1000 .
#1190
0!
#1195
1!
13
1/
04
b0 .
1,
b1000 .
#1200
0!
#1205
1!
03
0/
14
0,
b0 .
b1000 .
#1210
0!
#1215
1!
13
1/
04
b0 .
1,
b1000 .
#1220
0!
#1225
1!
03
0/
14
0,
b0 .
b1000 .
#1230
0!
#1235
1!
13
1/
04
b0 .
1,
b1000 .
#1240
0!
#1245
1!
03
0/
14
0,
b0 .
b1000 .
#1250
0!
#1255
1!
13
1/
04
b0 .
1,
b1000 .
#1260
0!
1%
0,
b0 .
1,
b1000 .
#1265
1!
03
0/
14
0,
b0 .
b1000 .
#1270
0!
#1275
1!
13
1/
04
b0 .
1,
b1000 .
#1280
0!
#1285
1!
03
0/
14
0,
b0 .
b1000 .
#1290
0!
#1295
1!
13
1/
04
b0 .
1,
b1000 .
#1300
0!
#1305
1!
03
0/
14
0,
b0 .
b1000 .
#1310
0!
#1315
1!
13
1/
04
b0 .
1,
b1000 .
#1320
0!
#1325
1!
03
0/
14
0,
b0 .
b1000 .
#1330
0!
#1335
1!
13
1/
04
b0 .
1,
b1000 .
